ax_generate_banner
fonts
