Metadata-Version: 2.1
Name: ax-generate-banner
Version: 0.1.4
Author: Baxromov
Author-email: baxromov.shahzodbek@gmail.com
Classifier: Development Status :: 3 - Alpha
Classifier: Intended Audience :: Developers
Classifier: Programming Language :: Python :: 3
